{
  "classname": null,
  "name": null,
  "animation": {
    "classname": null,
    "name": "AnimationManager",
    "actionlist": []
  },
  "dataScale": 1,
  "designHeight": 720,
  "designWidth": 1280,
  "textures": [],
  "texturesPng": [
    "{P7Q5((E5]C6%5$QK908COJ.jpg",
    "slice01_01.png",
    "Tower1_1.png",
    "delete.png",
    "456.png",
    "slice06_06.png",
    "1412063194_752391.png",
    "slice50_50.png",
    "jietu2.png",
    "slice06_06.png",
    "slice07_07.png",
    "S`B191P(RYW6R(@5EFRN1J6.jpg",
    "adasda.png",
    "asdsd.png"
  ],
  "version": "1.5.0.0",
  "widgetTree": {
    "classname": "Panel",
    "name": null,
    "children": [
      {
        "classname": "ImageView",
        "name": null,
        "children": [
          {
            "classname": "ImageView",
            "name": null,
            "children": [],
            "options": {
              "__type": "ImageViewSurrogate:#EditorCommon.JsonModel.Component.GUI",
              "classname": "ImageView",
              "name": "Image_3",
              "ZOrder": 0,
              "actiontag": 12544767,
              "anchorPointX": 0.5,
              "anchorPointY": 0.5,
              "classType": "CocoStudio.EngineAdapterWrap.CSImageView",
              "colorB": 255,
              "colorG": 255,
              "colorR": 255,
              "customProperty": "",
              "flipX": false,
              "flipY": false,
              "height": 410,
              "ignoreSize": true,
              "layoutParameter": null,
              "opacity": 255,
              "positionPercentX": 0.0537815131,
              "positionPercentY": 0.235474,
              "positionType": 0,
              "rotation": 0,
              "scaleX": 0.7208888,
              "scaleY": 0.393831283,
              "sizePercentX": 0.537815154,
              "sizePercentY": 1.25382268,
              "sizeType": 0,
              "tag": 191,
              "touchAble": false,
              "useMergedTexture": false,
              "visible": true,
              "width": 320,
              "x": 32,
              "y": 77,
              "capInsetsHeight": 1,
              "capInsetsWidth": 1,
              "capInsetsX": 0,
              "capInsetsY": 0,
              "fileName": null,
              "fileNameData": {
                "path": "asdsd.png",
                "plistFile": "",
                "resourceType": 0
              },
              "scale9Enable": false,
              "scale9Height": 410,
              "scale9Width": 320
            }
          }
        ],
        "options": {
          "__type": "ImageViewSurrogate:#EditorCommon.JsonModel.Component.GUI",
          "classname": "ImageView",
          "name": "Image_1",
          "ZOrder": 0,
          "actiontag": 1078370,
          "anchorPointX": 0.5,
          "anchorPointY": 0.5,
          "classType": "CocoStudio.EngineAdapterWrap.CSImageView",
          "colorB": 255,
          "colorG": 255,
          "colorR": 255,
          "customProperty": "",
          "flipX": false,
          "flipY": false,
          "height": 327,
          "ignoreSize": true,
          "layoutParameter": null,
          "opacity": 255,
          "positionPercentX": 0.478125,
          "positionPercentY": 0.405555546,
          "positionType": 0,
          "rotation": 0,
          "scaleX": 1.12325108,
          "scaleY": 1.44036567,
          "sizePercentX": 0.46484375,
          "sizePercentY": 0.454166681,
          "sizeType": 0,
          "tag": 189,
          "touchAble": false,
          "useMergedTexture": false,
          "visible": true,
          "width": 595,
          "x": 612,
          "y": 292,
          "capInsetsHeight": 1,
          "capInsetsWidth": 1,
          "capInsetsX": 0,
          "capInsetsY": 0,
          "fileName": null,
          "fileNameData": {
            "path": "adasda.png",
            "plistFile": "",
            "resourceType": 0
          },
          "scale9Enable": false,
          "scale9Height": 327,
          "scale9Width": 595
        }
      }
    ],
    "options": {
      "__type": "PanelSurrogate:#EditorCommon.JsonModel.Component.GUI",
      "classname": "Panel",
      "name": "Panel_6",
      "ZOrder": 0,
      "actiontag": -1,
      "anchorPointX": 0,
      "anchorPointY": 0,
      "classType": "CocoStudio.EngineAdapterWrap.CSPanel",
      "colorB": 255,
      "colorG": 255,
      "colorR": 255,
      "customProperty": "",
      "flipX": false,
      "flipY": false,
      "height": 720,
      "ignoreSize": false,
      "layoutParameter": null,
      "opacity": 255,
      "positionPercentX": 0,
      "positionPercentY": 0,
      "positionType": 0,
      "rotation": 0,
      "scaleX": 1,
      "scaleY": 1,
      "sizePercentX": 1,
      "sizePercentY": 1,
      "sizeType": 0,
      "tag": 188,
      "touchAble": false,
      "useMergedTexture": false,
      "visible": true,
      "width": 1280,
      "x": 0,
      "y": 0,
      "adaptScreen": true,
      "backGroundImage": null,
      "backGroundImageData": null,
      "backGroundScale9Enable": false,
      "bgColorB": 255,
      "bgColorG": 200,
      "bgColorOpacity": 0,
      "bgColorR": 150,
      "bgEndColorB": 255,
      "bgEndColorG": 200,
      "bgEndColorR": 150,
      "bgStartColorB": 255,
      "bgStartColorG": 255,
      "bgStartColorR": 255,
      "capInsetsHeight": 1,
      "capInsetsWidth": 1,
      "capInsetsX": 0,
      "capInsetsY": 0,
      "clipAble": false,
      "colorType": 1,
      "layoutType": 0,
      "vectorX": 0,
      "vectorY": -0.5
    }
  }
}